chialisp_loader.py
quex_chialisp_loader-0.1.2.dist-info/LICENSE
quex_chialisp_loader-0.1.2.dist-info/METADATA
quex_chialisp_loader-0.1.2.dist-info/WHEEL
quex_chialisp_loader-0.1.2.dist-info/top_level.txt
quex_chialisp_loader-0.1.2.dist-info/RECORD
