Metadata-Version: 2.1
Name: quex-chialisp-loader
Version: 0.1.2
Summary: Provides `load_puzzle` which dynamic rebuilds if `chialisp_builder` is available.
Author-email: Richard Kiss <him@richardkiss.com>
License: Copyright 2023 by Richard Kiss
License-File: LICENSE
Requires-Dist: clvm-rs
Requires-Dist: importlib-resources
